LFSR/LFSR.v
// 4-bit Linear Feedback Shift Register (LFSR)
// Feedback: bit0 = bit1 XOR bit3
module LFSR (
    input wire clk,
    input wire reset,
    output wire [3:0] lfsr_o
);

    // Internal register to hold LFSR state
    reg [3:0] lfsr_reg;
    
    // Feedback signal: XOR of bit1 and bit3
    wire feedback;
    assign feedback = lfsr_reg[1] ^ lfsr_reg[3];
    
    // Output assignment
    assign lfsr_o = lfsr_reg;
    
    // LFSR logic
    always @(posedge clk or posedge reset) begin
        if (reset) begin
            // Initialize with non-zero seed value
            lfsr_reg <= 4'b0001;
        end
        else begin
            // Shift operation with feedback
            lfsr_reg[0] <= feedback;      // bit0 gets feedback
            lfsr_reg[1] <= lfsr_reg[0];   // bit1 gets bit0
            lfsr_reg[2] <= lfsr_reg[1];   // bit2 gets bit1
            lfsr_reg[3] <= lfsr_reg[2];   // bit3 gets bit2
        end
    end

endmodule

LFSR/LFSR_tb.v
// Testbench for 4-bit LFSR
`timescale 1ns/1ps

module tb_LFSR;

    // Testbench signals
    reg clk;
    reg reset;
    wire [3:0] lfsr_o;
    
    // For tracking sequence
    reg [3:0] sequence [0:15];
    integer i;
    integer cycle_count;
    
    // Instantiate the LFSR
    LFSR dut (
        .clk(clk),
        .reset(reset),
        .lfsr_o(lfsr_o)
    );
    
    // Clock generation (10ns period = 100MHz)
    initial begin
        clk = 0;
        forever #5 clk = ~clk;
    end
    
    // Test sequence
    initial begin
        // Initialize
        reset = 1;
        cycle_count = 0;
        
        $display("\n=== 4-bit LFSR Testbench ===");
        $display("Feedback: bit0 = bit1 XOR bit3\n");
        $display("Cycle\tReset\tLFSR_Output\tBinary");
        $display("-----\t-----\t-----------\t------");
        
        // Apply reset
        #10 reset = 0;
        
        // Monitor LFSR output for multiple cycles
        for (i = 0; i < 20; i = i + 1) begin
            @(posedge clk);
            #1; // Small delay for signal stability
            $display("%0d\t%b\t%h\t\t%b", cycle_count, reset, lfsr_o, lfsr_o);
            sequence[cycle_count % 16] = lfsr_o;
            cycle_count = cycle_count + 1;
        end
        
        // Test reset functionality
        $display("\n--- Testing Reset ---");
        reset = 1;
        #10 reset = 0;
        @(posedge clk);
        #1;
        $display("After reset: LFSR = %b (should be 0001)", lfsr_o);
        
        // Continue for a few more cycles
        $display("\n--- Continuing Sequence ---");
        for (i = 0; i < 5; i = i + 1) begin
            @(posedge clk);
            #1;
            $display("%0d\t%b\t%h\t\t%b", cycle_count, reset, lfsr_o, lfsr_o);
            cycle_count = cycle_count + 1;
        end
        
        // Display sequence period
        $display("\n--- Sequence Analysis ---");
        $display("The LFSR generates a pseudo-random sequence.");
        $display("With XOR feedback from bit1 and bit3, the maximum");
        $display("sequence length is 15 states (2^4 - 1).");
        $display("\nNote: State 0000 is not part of the sequence");
        $display("(would lock up the LFSR).");
        
        $display("\n=== Test Complete ===\n");
        #20 $finish;
    end
    
    // Waveform dump
    initial begin
        $dumpfile("lfsr.vcd");
        $dumpvars(0, tb_LFSR);
    end
    
    // Check for lockup condition (all zeros)
    always @(posedge clk) begin
        if (!reset && lfsr_o == 4'b0000) begin
            $display("ERROR at time %0t: LFSR locked up at state 0000!", $time);
        end
    end

endmodule

LFSR/lfsr.vcd
$date
	Sat Oct 18 00:50:46 2025
$end
$version
	Icarus Verilog
$end
$timescale
	1ps
$end
$scope module tb_LFSR $end
$var wire 4 ! lfsr_o [3:0] $end
$var reg 1 " clk $end
$var reg 1 # reset $end
$var integer 32 $ cycle_count [31:0] $end
$var integer 32 % i [31:0] $end
$scope module dut $end
$var wire 1 " clk $end
$var wire 1 & feedback $end
$var wire 4 ' lfsr_o [3:0] $end
$var wire 1 # reset $end
$var reg 4 ( lfsr_reg [3:0] $end
$upscope $end
$upscope $end
$enddefinitions $end
$comment Show the parameter values. $end
$dumpall
$end
#0
$dumpvars
b1 (
b1 '
0&
bx %
b0 $
1#
0"
b1 !
$end
#5000
1"
#10000
0"
b0 %
0#
#15000
1&
b10 !
b10 '
b10 (
1"
#16000
b1 %
b1 $
#20000
0"
#25000
0&
b101 !
b101 '
b101 (
1"
#26000
b10 %
b10 $
#30000
0"
#35000
b1010 !
b1010 '
b1010 (
1"
#36000
b11 %
b11 $
#40000
0"
#45000
b100 !
b100 '
b100 (
1"
#46000
b100 %
b100 $
#50000
0"
#55000
1&
b1000 !
b1000 '
b1000 (
1"
#56000
b101 %
b101 $
#60000
0"
#65000
0&
b1 !
b1 '
b1 (
1"
#66000
b110 %
b110 $
#70000
0"
#75000
1&
b10 !
b10 '
b10 (
1"
#76000
b111 %
b111 $
#80000
0"
#85000
0&
b101 !
b101 '
b101 (
1"
#86000
b1000 %
b1000 $
#90000
0"
#95000
b1010 !
b1010 '
b1010 (
1"
#96000
b1001 %
b1001 $
#100000
0"
#105000
b100 !
b100 '
b100 (
1"
#106000
b1010 %
b1010 $
#110000
0"
#115000
1&
b1000 !
b1000 '
b1000 (
1"
#116000
b1011 %
b1011 $
#120000
0"
#125000
0&
b1 !
b1 '
b1 (
1"
#126000
b1100 %
b1100 $
#130000
0"
#135000
1&
b10 !
b10 '
b10 (
1"
#136000
b1101 %
b1101 $
#140000
0"
#145000
0&
b101 !
b101 '
b101 (
1"
#146000
b1110 %
b1110 $
#150000
0"
#155000
b1010 !
b1010 '
b1010 (
1"
#156000
b1111 %
b1111 $
#160000
0"
#165000
b100 !
b100 '
b100 (
1"
#166000
b10000 %
b10000 $
#170000
0"
#175000
1&
b1000 !
b1000 '
b1000 (
1"
#176000
b10001 %
b10001 $
#180000
0"
#185000
0&
b1 !
b1 '
b1 (
1"
#186000
b10010 %
b10010 $
#190000
0"
#195000
1&
b10 !
b10 '
b10 (
1"
#196000
b10011 %
b10011 $
#200000
0"
#205000
0&
b101 !
b101 '
b101 (
1"
#206000
b1 !
b1 '
b1 (
1#
b10100 %
b10100 $
#210000
0"
#215000
1"
#216000
0#
#220000
0"
#225000
1&
b10 !
b10 '
b10 (
1"
#226000
b0 %
#230000
0"
#235000
0&
b101 !
b101 '
b101 (
1"
#236000
b1 %
b10101 $
#240000
0"
#245000
b1010 !
b1010 '
b1010 (
1"
#246000
b10 %
b10110 $
#250000
0"
#255000
b100 !
b100 '
b100 (
1"
#256000
b11 %
b10111 $
#260000
0"
#265000
1&
b1000 !
b1000 '
b1000 (
1"
#266000
b100 %
b11000 $
#270000
0"
#275000
0&
b1 !
b1 '
b1 (
1"
#276000
b101 %
b11001 $
#280000
0"
#285000
1&
b10 !
b10 '
b10 (
1"
#290000
0"
#295000
0&
b101 !
b101 '
b101 (
1"
