Parallel_to_Serial/PS.v
// 4-bit Parallel to Serial Converter
module parallel_to_serial (
    input wire clk,           // Clock signal
    input wire rst,           // Active high reset
    input wire load,          // Load parallel data
    input wire [3:0] p_data,  // 4-bit parallel input data
    output reg s_data,        // Serial output data
    output reg valid,         // Valid signal (data is being transmitted)
    output reg empty          // Empty signal (no data to transmit)
);

    reg [3:0] shift_reg;      // Shift register to hold data
    reg [2:0] bit_count;      // Counter for bits transmitted (0-3)

    always @(posedge clk or posedge rst) begin
        if (rst) begin
            shift_reg <= 4'b0000;
            s_data <= 1'b0;
            valid <= 1'b0;
            empty <= 1'b1;
            bit_count <= 3'd0;
        end
        else if (load) begin
            // Load parallel data into shift register
            shift_reg <= p_data;
            s_data <= p_data[0];  // Output LSB first
            valid <= 1'b1;
            empty <= 1'b0;
            bit_count <= 3'd0;
        end
        else if (!empty) begin
            // Shift and output next bit
            bit_count <= bit_count + 1;
            if (bit_count < 3'd3) begin
                shift_reg <= shift_reg >> 1;  // Shift right
                s_data <= shift_reg[1];       // Output next bit
                valid <= 1'b1;
            end
            else begin
                // All bits transmitted
                valid <= 1'b0;
                empty <= 1'b1;
                s_data <= 1'b0;
            end
        end
        else begin
            valid <= 1'b0;
            empty <= 1'b1;
        end
    end

endmodule

Parallel_to_Serial/PS_tb.v
// Testbench for 4-bit Parallel to Serial Converter
`timescale 1ns/1ps

module tb_parallel_to_serial;

    // Testbench signals
    reg clk;
    reg rst;
    reg load;
    reg [3:0] p_data;
    wire s_data;
    wire valid;
    wire empty;

    // Instantiate the DUT (Device Under Test)
    parallel_to_serial dut (
        .clk(clk),
        .rst(rst),
        .load(load),
        .p_data(p_data),
        .s_data(s_data),
        .valid(valid),
        .empty(empty)
    );

    // Clock generation (10ns period = 100MHz)
    initial begin
        clk = 0;
        forever #5 clk = ~clk;
    end

    // Test sequence
    initial begin
        // Initialize signals
        rst = 0;
        load = 0;
        p_data = 4'b0000;

        // Display header
        $display("Time\tRst\tLoad\tP_Data\tS_Data\tValid\tEmpty\tBit_Count");
        $monitor("%0t\t%b\t%b\t%b\t%b\t%b\t%b", 
                 $time, rst, load, p_data, s_data, valid, empty);

        // Test 1: Reset
        #10 rst = 1;
        #10 rst = 0;
        $display("\n--- Test 1: Reset Complete ---");

        // Test 2: Load data 1010
        #10 p_data = 4'b1010;
        load = 1;
        #10 load = 0;
        $display("\n--- Test 2: Loading 1010 ---");
        
        // Wait for all bits to be transmitted
        #50;

        // Test 3: Load data 1111
        #10 p_data = 4'b1111;
        load = 1;
        #10 load = 0;
        $display("\n--- Test 3: Loading 1111 ---");
        
        #50;

        // Test 4: Load data 0101
        #10 p_data = 4'b0101;
        load = 1;
        #10 load = 0;
        $display("\n--- Test 4: Loading 0101 ---");
        
        #50;

        // Test 5: Check empty state
        $display("\n--- Test 5: Verify Empty State ---");
        #20;

        $display("\n--- All Tests Complete ---");
        $finish;
    end

    // Waveform dump for viewing in GTKWave or similar
    initial begin
        $dumpfile("parallel_to_serial.vcd");
        $dumpvars(0, tb_parallel_to_serial);
    end

endmodule

Parallel_to_Serial/parallel_to_serial.vcd
$date
	Fri Oct 17 23:52:11 2025
$end
$version
	Icarus Verilog
$end
$timescale
	1ps
$end
$scope module tb_parallel_to_serial $end
$var wire 1 ! valid $end
$var wire 1 " s_data $end
$var wire 1 # empty $end
$var reg 1 $ clk $end
$var reg 1 % load $end
$var reg 4 & p_data [3:0] $end
$var reg 1 ' rst $end
$scope module dut $end
$var wire 1 $ clk $end
$var wire 1 % load $end
$var wire 4 ( p_data [3:0] $end
$var wire 1 ' rst $end
$var reg 3 ) bit_count [2:0] $end
$var reg 1 # empty $end
$var reg 1 " s_data $end
$var reg 4 * shift_reg [3:0] $end
$var reg 1 ! valid $end
$upscope $end
$upscope $end
$enddefinitions $end
$comment Show the parameter values. $end
$dumpall
$end
#0
$dumpvars
bx *
bx )
b0 (
0'
b0 &
0%
0$
x#
x"
x!
$end
#5000
1#
0!
1$
#10000
b0 )
0"
b0 *
0$
1'
#15000
1$
#20000
0$
0'
#25000
1$
#30000
0$
1%
b1010 &
b1010 (
#35000
0#
1!
b1010 *
1$
#40000
0$
0%
#45000
1"
b101 *
b1 )
1$
#50000
0$
#55000
0"
b10 *
b10 )
1$
#60000
0$
#65000
1"
b1 *
b11 )
1$
#70000
0$
#75000
0"
1#
0!
b100 )
1$
#80000
0$
#85000
1$
#90000
0$
#95000
1$
#100000
0$
1%
b1111 &
b1111 (
#105000
b0 )
0#
1!
1"
b1111 *
1$
#110000
0$
0%
#115000
b111 *
b1 )
1$
#120000
0$
#125000
b11 *
b10 )
1$
#130000
0$
#135000
b1 *
b11 )
1$
#140000
0$
#145000
0"
1#
0!
b100 )
1$
#150000
0$
#155000
1$
#160000
0$
#165000
1$
#170000
0$
1%
b101 &
b101 (
#175000
b0 )
0#
1!
1"
b101 *
1$
#180000
0$
0%
#185000
0"
b10 *
b1 )
1$
#190000
0$
#195000
1"
b1 *
b10 )
1$
#200000
0$
#205000
0"
b0 *
b11 )
1$
#210000
0$
#215000
1#
0!
b100 )
1$
