Synchronous_FIFO/fifo.v
// Synchronous FIFO - 8-bit wide, 16 entries deep
module sync_fifo #(
    parameter DATA_WIDTH = 8,
    parameter DEPTH = 16,
    parameter ADDR_WIDTH = 4  // log2(DEPTH)
)(
    input wire clk,                          // Clock
    input wire rst,                          // Active high reset
    input wire wr_en,                        // Write enable
    input wire rd_en,                        // Read enable
    input wire [DATA_WIDTH-1:0] wr_data,     // Write data
    output reg [DATA_WIDTH-1:0] rd_data,     // Read data
    output wire full,                        // FIFO full flag
    output wire empty,                       // FIFO empty flag
    output wire [ADDR_WIDTH:0] data_count    // Number of items in FIFO
);

    // Internal memory array
    reg [DATA_WIDTH-1:0] fifo_mem [0:DEPTH-1];
    
    // Read and write pointers
    reg [ADDR_WIDTH-1:0] wr_ptr;
    reg [ADDR_WIDTH-1:0] rd_ptr;
    
    // Internal counter for number of elements
    reg [ADDR_WIDTH:0] count;
    
    // Flag assignments
    assign full = (count == DEPTH);
    assign empty = (count == 0);
    assign data_count = count;  // Wire assignment from internal counter
    
    // Write operation
    always @(posedge clk or posedge rst) begin
        if (rst) begin
            wr_ptr <= 0;
        end
        else if (wr_en && !full) begin
            fifo_mem[wr_ptr] <= wr_data;
            wr_ptr <= wr_ptr + 1;
        end
    end
    
    // Read operation
    always @(posedge clk or posedge rst) begin
        if (rst) begin
            rd_ptr <= 0;
            rd_data <= 0;
        end
        else if (rd_en && !empty) begin
            rd_data <= fifo_mem[rd_ptr];
            rd_ptr <= rd_ptr + 1;
        end
    end
    
    // Counter logic
    always @(posedge clk or posedge rst) begin
        if (rst) begin
            count <= 0;
        end
        else begin
            case ({wr_en && !full, rd_en && !empty})
                2'b10: count <= count + 1;  // Write only
                2'b01: count <= count - 1;  // Read only
                2'b11: count <= count;      // Simultaneous read/write
                default: count <= count;    // No operation
            endcase
        end
    end

endmodule

Synchronous_FIFO/fifo_tb.v
// Testbench for Synchronous FIFO
`timescale 1ns/1ps

module tb_sync_fifo;

    // Parameters
    parameter DATA_WIDTH = 8;
    parameter DEPTH = 16;
    parameter ADDR_WIDTH = 4;
    parameter CLK_PERIOD = 10;
    
    // Testbench signals
    reg clk;
    reg rst;
    reg wr_en;
    reg rd_en;
    reg [DATA_WIDTH-1:0] wr_data;
    wire [DATA_WIDTH-1:0] rd_data;
    wire full;
    wire empty;
    wire [ADDR_WIDTH:0] data_count;
    
    // Instantiate the FIFO
    sync_fifo #(
        .DATA_WIDTH(DATA_WIDTH),
        .DEPTH(DEPTH),
        .ADDR_WIDTH(ADDR_WIDTH)
    ) dut (
        .clk(clk),
        .rst(rst),
        .wr_en(wr_en),
        .rd_en(rd_en),
        .wr_data(wr_data),
        .rd_data(rd_data),
        .full(full),
        .empty(empty),
        .data_count(data_count)
    );
    
    // Clock generation
    initial begin
        clk = 0;
        forever #(CLK_PERIOD/2) clk = ~clk;
    end
    
    // Test sequence
    initial begin
        // Initialize signals
        rst = 1;
        wr_en = 0;
        rd_en = 0;
        wr_data = 0;
        
        // Display header
        $display("\n=== Synchronous FIFO Testbench ===\n");
        $display("Time\tRst\tWr_En\tRd_En\tWr_Data\tRd_Data\tFull\tEmpty\tCount");
        $monitor("%0t\t%b\t%b\t%b\t%h\t%h\t%b\t%b\t%0d", 
                 $time, rst, wr_en, rd_en, wr_data, rd_data, full, empty, data_count);
        
        // Test 1: Reset
        #(CLK_PERIOD*2);
        rst = 0;
        #(CLK_PERIOD);
        $display("\n--- Test 1: Reset Complete ---");
        
        // Test 2: Write data to FIFO
        $display("\n--- Test 2: Writing 10 values to FIFO ---");
        repeat(10) begin
            @(posedge clk);
            wr_en = 1;
            wr_data = wr_data + 8'h11;
        end
        @(posedge clk);
        wr_en = 0;
        
        // Test 3: Read 5 values
        $display("\n--- Test 3: Reading 5 values from FIFO ---");
        #(CLK_PERIOD*2);
        repeat(5) begin
            @(posedge clk);
            rd_en = 1;
        end
        @(posedge clk);
        rd_en = 0;
        
        // Test 4: Simultaneous read and write
        $display("\n--- Test 4: Simultaneous Read and Write ---");
        #(CLK_PERIOD*2);
        repeat(5) begin
            @(posedge clk);
            wr_en = 1;
            rd_en = 1;
            wr_data = wr_data + 8'h11;
        end
        @(posedge clk);
        wr_en = 0;
        rd_en = 0;
        
        // Test 5: Fill FIFO completely
        $display("\n--- Test 5: Filling FIFO completely ---");
        #(CLK_PERIOD*2);
        wr_data = 8'hAA;
        repeat(20) begin  // Try to write more than capacity
            @(posedge clk);
            wr_en = 1;
            wr_data = wr_data + 1;
        end
        @(posedge clk);
        wr_en = 0;
        
        // Test 6: Empty FIFO completely
        $display("\n--- Test 6: Emptying FIFO completely ---");
        #(CLK_PERIOD*2);
        repeat(20) begin  // Try to read more than available
            @(posedge clk);
            rd_en = 1;
        end
        @(posedge clk);
        rd_en = 0;
        
        // Test 7: Check empty flag
        $display("\n--- Test 7: Verify Empty State ---");
        #(CLK_PERIOD*3);
        
        $display("\n=== All Tests Complete ===\n");
        #(CLK_PERIOD*5);
        $finish;
    end
    
    // Waveform dump
    initial begin
        $dumpfile("sync_fifo.vcd");
        $dumpvars(0, tb_sync_fifo);
    end
    
    // Check for overflow/underflow
    always @(posedge clk) begin
        if (wr_en && full)
            $display("WARNING at %0t: Write attempted when FIFO is FULL!", $time);
        if (rd_en && empty)
            $display("WARNING at %0t: Read attempted when FIFO is EMPTY!", $time);
    end

endmodule

Synchronous_FIFO/sync_fifo.vcd
$date
	Sat Oct 18 00:33:48 2025
$end
$version
	Icarus Verilog
$end
$timescale
	1ps
$end
$scope module tb_sync_fifo $end
$var wire 8 ! rd_data [7:0] $end
$var wire 1 " full $end
$var wire 1 # empty $end
$var wire 5 $ data_count [4:0] $end
$var parameter 32 % ADDR_WIDTH $end
$var parameter 32 & CLK_PERIOD $end
$var parameter 32 ' DATA_WIDTH $end
$var parameter 32 ( DEPTH $end
$var reg 1 ) clk $end
$var reg 1 * rd_en $end
$var reg 1 + rst $end
$var reg 8 , wr_data [7:0] $end
$var reg 1 - wr_en $end
$scope module dut $end
$var wire 1 ) clk $end
$var wire 5 . data_count [4:0] $end
$var wire 1 * rd_en $end
$var wire 1 + rst $end
$var wire 8 / wr_data [7:0] $end
$var wire 1 - wr_en $end
$var wire 1 " full $end
$var wire 1 # empty $end
$var parameter 32 0 ADDR_WIDTH $end
$var parameter 32 1 DATA_WIDTH $end
$var parameter 32 2 DEPTH $end
$var reg 5 3 count [4:0] $end
$var reg 8 4 rd_data [7:0] $end
$var reg 4 5 rd_ptr [3:0] $end
$var reg 4 6 wr_ptr [3:0] $end
$upscope $end
$upscope $end
$enddefinitions $end
$comment Show the parameter values. $end
$dumpall
b10000 2
b1000 1
b100 0
b10000 (
b1000 '
b1010 &
b100 %
$end
#0
$dumpvars
b0 6
b0 5
b0 4
b0 3
b0 /
b0 .
0-
b0 ,
1+
0*
0)
b0 $
1#
0"
b0 !
$end
#5000
1)
#10000
0)
#15000
1)
#20000
0)
0+
#25000
1)
#30000
0)
#35000
b1 6
0#
b1 $
b1 .
b1 3
b10001 ,
b10001 /
1-
1)
#40000
0)
#45000
b10 $
b10 .
b10 3
b10 6
b100010 ,
b100010 /
1)
#50000
0)
#55000
b11 6
b11 $
b11 .
b11 3
b110011 ,
b110011 /
1)
#60000
0)
#65000
b100 $
b100 .
b100 3
b100 6
b1000100 ,
b1000100 /
1)
#70000
0)
#75000
b101 6
b101 $
b101 .
b101 3
b1010101 ,
b1010101 /
1)
#80000
0)
#85000
b110 $
b110 .
b110 3
b110 6
b1100110 ,
b1100110 /
1)
#90000
0)
#95000
b111 6
b111 $
b111 .
b111 3
b1110111 ,
b1110111 /
1)
#100000
0)
#105000
b1000 $
b1000 .
b1000 3
b1000 6
b10001000 ,
b10001000 /
1)
#110000
0)
#115000
b1001 6
b1001 $
b1001 .
b1001 3
b10011001 ,
b10011001 /
1)
#120000
0)
#125000
b1010 $
b1010 .
b1010 3
b1010 6
b10101010 ,
b10101010 /
1)
#130000
0)
#135000
0-
1)
#140000
0)
#145000
1)
#150000
0)
#155000
b1 5
b10001 !
b10001 4
b1001 $
b1001 .
b1001 3
1*
1)
#160000
0)
#165000
b1000 $
b1000 .
b1000 3
b10 5
b100010 !
b100010 4
1)
#170000
0)
#175000
b11 5
b110011 !
b110011 4
b111 $
b111 .
b111 3
1)
#180000
0)
#185000
b110 $
b110 .
b110 3
b100 5
b1000100 !
b1000100 4
1)
#190000
0)
#195000
b101 5
b1010101 !
b1010101 4
b101 $
b101 .
b101 3
1)
#200000
0)
#205000
0*
1)
#210000
0)
#215000
1)
#220000
0)
#225000
b110 5
b1100110 !
b1100110 4
b1011 6
b10111011 ,
b10111011 /
1*
1-
1)
#230000
0)
#235000
b1100 6
b111 5
b1110111 !
b1110111 4
b11001100 ,
b11001100 /
1)
#240000
0)
#245000
b1000 5
b10001000 !
b10001000 4
b1101 6
b11011101 ,
b11011101 /
1)
#250000
0)
#255000
b1110 6
b1001 5
b10011001 !
b10011001 4
b11101110 ,
b11101110 /
1)
#260000
0)
#265000
b1010 5
b10101010 !
b10101010 4
b1111 6
b11111111 ,
b11111111 /
1)
#270000
0)
#275000
0*
0-
1)
#280000
0)
#285000
1)
#290000
0)
#295000
b0 6
b110 $
b110 .
b110 3
1-
1)
b10101011 ,
b10101011 /
#300000
0)
#305000
b111 $
b111 .
b111 3
b1 6
b10101100 ,
b10101100 /
1)
#310000
0)
#315000
b10 6
b1000 $
b1000 .
b1000 3
b10101101 ,
b10101101 /
1)
#320000
0)
#325000
b1001 $
b1001 .
b1001 3
b11 6
b10101110 ,
b10101110 /
1)
#330000
0)
#335000
b100 6
b1010 $
b1010 .
b1010 3
b10101111 ,
b10101111 /
1)
#340000
0)
#345000
b1011 $
b1011 .
b1011 3
b101 6
b10110000 ,
b10110000 /
1)
#350000
0)
#355000
b110 6
b1100 $
b1100 .
b1100 3
b10110001 ,
b10110001 /
1)
#360000
0)
#365000
b1101 $
b1101 .
b1101 3
b111 6
b10110010 ,
b10110010 /
1)
#370000
0)
#375000
b1000 6
b1110 $
b1110 .
b1110 3
b10110011 ,
b10110011 /
1)
#380000
0)
#385000
b1111 $
b1111 .
b1111 3
b1001 6
b10110100 ,
b10110100 /
1)
#390000
0)
#395000
b1010 6
1"
b10000 $
b10000 .
b10000 3
b10110101 ,
b10110101 /
1)
#400000
0)
#405000
b10110110 ,
b10110110 /
1)
#410000
0)
#415000
b10110111 ,
b10110111 /
1)
#420000
0)
#425000
b10111000 ,
b10111000 /
1)
#430000
0)
#435000
b10111001 ,
b10111001 /
1)
#440000
0)
#445000
b10111010 ,
b10111010 /
1)
#450000
0)
#455000
b10111011 ,
b10111011 /
1)
#460000
0)
#465000
b10111100 ,
b10111100 /
1)
#470000
0)
#475000
b10111101 ,
b10111101 /
1)
#480000
0)
#485000
b10111110 ,
b10111110 /
1)
#490000
0)
#495000
0-
1)
#500000
0)
#505000
1)
#510000
0)
#515000
b1011 5
b10111011 !
b10111011 4
0"
b1111 $
b1111 .
b1111 3
1*
1)
#520000
0)
#525000
b1110 $
b1110 .
b1110 3
b1100 5
b11001100 !
b11001100 4
1)
#530000
0)
#535000
b1101 5
b11011101 !
b11011101 4
b1101 $
b1101 .
b1101 3
1)
#540000
0)
#545000
b1100 $
b1100 .
b1100 3
b1110 5
b11101110 !
b11101110 4
1)
#550000
0)
#555000
b1111 5
b11111111 !
b11111111 4
b1011 $
b1011 .
b1011 3
1)
#560000
0)
#565000
b1010 $
b1010 .
b1010 3
b0 5
b10101011 !
b10101011 4
1)
#570000
0)
#575000
b1 5
b10101100 !
b10101100 4
b1001 $
b1001 .
b1001 3
1)
#580000
0)
#585000
b1000 $
b1000 .
b1000 3
b10 5
b10101101 !
b10101101 4
1)
#590000
0)
#595000
b11 5
b10101110 !
b10101110 4
b111 $
b111 .
b111 3
1)
#600000
0)
#605000
b110 $
b110 .
b110 3
b100 5
b10101111 !
b10101111 4
1)
#610000
0)
#615000
b101 5
b10110000 !
b10110000 4
b101 $
b101 .
b101 3
1)
#620000
0)
#625000
b100 $
b100 .
b100 3
b110 5
b10110001 !
b10110001 4
1)
#630000
0)
#635000
b111 5
b10110010 !
b10110010 4
b11 $
b11 .
b11 3
1)
#640000
0)
#645000
b10 $
b10 .
b10 3
b1000 5
b10110011 !
b10110011 4
1)
#650000
0)
#655000
b1001 5
b10110100 !
b10110100 4
b1 $
b1 .
b1 3
1)
#660000
0)
#665000
1#
b0 $
b0 .
b0 3
b1010 5
b10110101 !
b10110101 4
1)
#670000
0)
#675000
1)
#680000
0)
#685000
1)
#690000
0)
#695000
1)
#700000
0)
#705000
1)
#710000
0)
#715000
0*
1)
