Shift_Register/Shift_register.v
module Shift_Register(
    input wire clk,
    input wire reset,
    input wire x_i,
    output reg [3:0] sr_o
);

always @(posedge clk or posedge reset) begin
    if (reset) begin
        sr_o <= 4'b0000;
    end else begin
        sr_o <= {sr_o[2:0], x_i};  // Shift left, insert x_i at LSB
    end
end

endmodule

Shift_Register/testbench.v
// Testbench for the 4-bit Shift Register module
// This file tests the functionality of Shift_Register.v

`timescale 1ns/1ps

module testbench;
    // --- Signals needed for the testbench ---
    // These `reg` signals drive the inputs of your module-under-test (DUT)
    reg clk;
    reg reset;
    reg x_i;

    // These `wire` signals monitor the outputs of your DUT
    wire [3:0] sr_o;

    // --- Instantiate the module under test (DUT) ---
    // This connects the testbench signals to the module's ports
    Shift_Register DUT (
        .clk(clk),
        .reset(reset),
        .x_i(x_i),
        .sr_o(sr_o)
    );

    // --- Clock generation ---
    // The `initial` and `forever` blocks create a free-running clock signal
    // It starts at 0 and toggles every 5 time units (5 ns), giving a 10 ns period.
    initial begin
        clk = 0;
        forever #5 clk = ~clk; 
    end

    // --- Test scenario ---
    // The `initial` block defines the test sequence for inputs
    initial begin
        // --- 1. Generate waveform data ---
        // These system tasks tell the simulator to create a VCD file
        // that can be viewed in a waveform viewer like GTKWave.
        $dumpfile("dump.vcd");
        $dumpvars(0, testbench);

        // --- 2. Initial state and reset ---
        reset = 1;     // Assert reset
        x_i = 0;       // Set x_i to a known value
        #10;           // Hold reset for 10 ns (one full clock cycle)
        reset = 0;     // De-assert reset
        #10;           // Wait for one clock cycle to observe a cleared state

        // --- 3. Shift in a sequence of bits ---
        // The following sequence shifts in the binary pattern '1011'
        // First bit: '1'
        x_i = 1;
        #10;

        // Second bit: '0'
        x_i = 0;
        #10;

        // Third bit: '1'
        x_i = 1;
        #10;

        // Fourth bit: '1'
        x_i = 1;
        #10;

        // --- 4. Final state and simulation end ---
        // Wait a few more cycles to observe the final state
        #20;

        // End the simulation
        $finish;
    end

endmodule

Shift_Register/dump.vcd
$date
	Fri Oct 17 22:17:44 2025
$end
$version
	Icarus Verilog
$end
$timescale
	1ps
$end
$scope module testbench $end
$var wire 4 ! sr_o [3:0] $end
$var reg 1 " clk $end
$var reg 1 # reset $end
$var reg 1 $ x_i $end
$scope module DUT $end
$var wire 1 " clk $end
$var wire 1 # reset $end
$var wire 1 $ x_i $end
$var reg 4 % sr_o [3:0] $end
$upscope $end
$upscope $end
$enddefinitions $end
$comment Show the parameter values. $end
$dumpall
$end
#0
$dumpvars
b0 %
0$
1#
0"
b0 !
$end
#5000
1"
#10000
0"
0#
#15000
1"
#20000
0"
1$
#25000
b1 !
b1 %
1"
#30000
0"
0$
#35000
b10 !
b10 %
1"
#40000
0"
1$
#45000
b101 !
b101 %
1"
#50000
0"
#55000
b1011 !
b1011 %
1"
#60000
0"
#65000
b111 !
b111 %
1"
#70000
0"
#75000
b1111 !
b1111 %
1"
