Shift_Register/Shift_register.v
module Shift_Register(
    input wire clk,
    input wire reset,
    input wire x_i,
    output reg [3:0] sr_o
);

always @(posedge clk or posedge reset) begin
    if (reset) begin
        sr_o <= 4'b0000;
    end else begin
        sr_o <= {sr_o[2:0], x_i};  // Shift left, insert x_i at LSB
    end
end

endmodule

Shift_Register/testbench.v
`timescale 1ns/1ns

module Shift_Register_tb;

// Testbench signals
reg clk;
reg reset;
reg x_i;
wire [3:0] sr_o;

// Instantiate the Shift Register module
Shift_Register uut (
    .clk(clk),
    .reset(reset),
    .x_i(x_i),
    .sr_o(sr_o)
);

// Clock generation - 10ns period (100MHz)
initial begin
    clk = 0;
    forever #5 clk = ~clk;
end

// Test sequence
initial begin
    // Initialize signals
    reset = 1;
    x_i = 0;
    
    // Display header
    $display("Time\tReset\tx_i\tsr_o");
    $display("====\t=====\t===\t====");
    
    // Wait for a few clock cycles with reset active
    #10;
    reset = 0;
    
    // Test Case 1: Shift in sequence 1011
    #10 x_i = 1; $display("%0t\t%b\t%b\t%b", $time, reset, x_i, sr_o);
    #10 x_i = 0; $display("%0t\t%b\t%b\t%b", $time, reset, x_i, sr_o);
    #10 x_i = 1; $display("%0t\t%b\t%b\t%b", $time, reset, x_i, sr_o);
    #10 x_i = 1; $display("%0t\t%b\t%b\t%b", $time, reset, x_i, sr_o);
    
    // Test Case 2: Continue shifting with 0s
    #10 x_i = 0; $display("%0t\t%b\t%b\t%b", $time, reset, x_i, sr_o);
    #10 x_i = 0; $display("%0t\t%b\t%b\t%b", $time, reset, x_i, sr_o);
    
    // Test Case 3: Test reset functionality
    #10 reset = 1; $display("%0t\t%b\t%b\t%b", $time, reset, x_i, sr_o);
    #10 reset = 0; $display("%0t\t%b\t%b\t%b", $time, reset, x_i, sr_o);
    
    // Test Case 4: Shift in all 1s
    #10 x_i = 1; $display("%0t\t%b\t%b\t%b", $time, reset, x_i, sr_o);
    #10 x_i = 1; $display("%0t\t%b\t%b\t%b", $time, reset, x_i, sr_o);
    #10 x_i = 1; $display("%0t\t%b\t%b\t%b", $time, reset, x_i, sr_o);
    #10 x_i = 1; $display("%0t\t%b\t%b\t%b", $time, reset, x_i, sr_o);
    
    // Wait and finish
    #20;
    $display("\nTestbench completed successfully!");
    $finish;
end

// Optional: Generate VCD file for waveform viewing
initial begin
    $dumpfile("shift_register.vcd");
    $dumpvars(0, Shift_Register_tb);
end

endmodule

Shift_Register/shift_register.vcd
$date
	Fri Oct 17 22:45:08 2025
$end
$version
	Icarus Verilog
$end
$timescale
	1ns
$end
$scope module Shift_Register_tb $end
$var wire 4 ! sr_o [3:0] $end
$var reg 1 " clk $end
$var reg 1 # reset $end
$var reg 1 $ x_i $end
$scope module uut $end
$var wire 1 " clk $end
$var wire 1 # reset $end
$var wire 1 $ x_i $end
$var reg 4 % sr_o [3:0] $end
$upscope $end
$upscope $end
$enddefinitions $end
$comment Show the parameter values. $end
$dumpall
$end
#0
$dumpvars
b0 %
0$
1#
0"
b0 !
$end
#5
1"
#10
0"
0#
#15
1"
#20
0"
1$
#25
b1 !
b1 %
1"
#30
0"
0$
#35
b10 !
b10 %
1"
#40
0"
1$
#45
b101 !
b101 %
1"
#50
0"
#55
b1011 !
b1011 %
1"
#60
0"
0$
#65
b110 !
b110 %
1"
#70
0"
#75
b1100 !
b1100 %
1"
#80
b0 !
b0 %
0"
1#
#85
1"
#90
0"
0#
#95
1"
#100
0"
1$
#105
b1 !
b1 %
1"
#110
0"
#115
b11 !
b11 %
1"
#120
0"
#125
b111 !
b111 %
1"
#130
0"
#135
b1111 !
b1111 %
1"
